galaxy/app/__init__.py
galaxy/app/app.py
galaxy/app/argparser.py
galaxy/app/constant.py
galaxy/app/ioc/__init__.py
galaxy/app/ioc/builder.py
galaxy/app/ioc/definition.py
galaxy/app/ioc/factory.py
galaxy/app/ioc/ioc.py
galaxy/app/ioc/parser.py
galaxy/app/ioc/visitor.py
galaxy/app/test/test_jupyter_client.py
galaxy/app/test/test_jupyter_kernel.py
galaxy/app/test/test_simple_app.py
galaxy_py_app-0.0.9.dist-info/AUTHORS
galaxy_py_app-0.0.9.dist-info/COPYING.md
galaxy_py_app-0.0.9.dist-info/LICENSE.txt
galaxy_py_app-0.0.9.dist-info/METADATA
galaxy_py_app-0.0.9.dist-info/WHEEL
galaxy_py_app-0.0.9.dist-info/RECORD
